bvrajuPackage1/__init__.py
bvrajuPackage1/myModule1.py
bvrajuPackage1/myModule2.py
myFirstPackageDatapro-0.1.dist-info/METADATA
myFirstPackageDatapro-0.1.dist-info/WHEEL
myFirstPackageDatapro-0.1.dist-info/top_level.txt
myFirstPackageDatapro-0.1.dist-info/RECORD
