Metadata-Version: 2.1
Name: myFirstPackageDatapro
Version: 0.1
Summary: Package created by BVRaju datapro for testing
Home-page: https://dataproelearn.com/
Author: BVRaju
Author-email: bvraju.itp@gmail.com
License: UNKNOWN
Platform: UNKNOWN
Requires-Python: >=3.0
